imgmeta/__init__.py
imgmeta/database.py
imgmeta/helper.py
imgmeta/meta.py
imgmeta-0.1.1.dist-info/WHEEL
imgmeta-0.1.1.dist-info/METADATA
imgmeta-0.1.1.dist-info/RECORD
