Metadata-Version: 2.1
Name: imgmeta
Version: 0.1.1
Summary: 
Author: Bao Hengtao
Author-email: baohengtao@users.noreply.github.com
Requires-Python: >=3.9,<4.0
Classifier: Programming Language :: Python :: 3
Classifier: Programming Language :: Python :: 3.9
Requires-Dist: click (>=8.0.1,<9.0.0)
Requires-Dist: geopy (>=2.2.0,<3.0.0)
Requires-Dist: loguru (>=0.5.3,<0.6.0)
Requires-Dist: osxphotos (>=0.42.80,<0.43.0)
Requires-Dist: photoscript (>=0.1.4,<0.2.0)
Requires-Dist: pymongo (>=3.12.0,<4.0.0)
Requires-Dist: sinaspider (>=0.3.2,<0.4.0)
